dependencytrack_client/__init__.py
dependencytrack_client/components.py
dependencytrack_client/exceptions.py
dependencytrack_client/licenses.py
dependencytrack_client/projects.py
dependencytrack_client/version.py
dependencytrack_client/violations.py
dependency_track_client-4.0.3.dist-info/LICENSE.md
dependency_track_client-4.0.3.dist-info/METADATA
dependency_track_client-4.0.3.dist-info/WHEEL
dependency_track_client-4.0.3.dist-info/top_level.txt
dependency_track_client-4.0.3.dist-info/RECORD
