Metadata-Version: 2.2
Name: dependency-track-client
Version: 4.0.3
Summary: A simple wrapper for the Dependency Track REST API. This is fork based on original work of Alvin Chen and his dependency-track library.
Author-email: Alvin Chen <sonoma001@gmail.com>, Lumir Jasiok <lumir.jasiok@alfawolf.eu>, Louis Marie <louis.marie@orange.com>
Project-URL: Homepage, https://github.com/Orange-OpenSource/dependency-track-python
Project-URL: Issues, https://github.com/Orange-OpenSource/dependency-track-python/issues
Classifier: Programming Language :: Python :: 3
Classifier: License :: OSI Approved :: GNU General Public License v2 (GPLv2)
Classifier: Operating System :: OS Independent
Requires-Python: >=3.8
License-File: LICENSE.md
Requires-Dist: requests>=2.31.0
